vior_cli/__init__.py
vior_cli/api_client.py
vior_cli/cli.py
vior_cli/config_manager.py
vior_cli-1.0.8.dist-info/licenses/LICENSE
vior_cli-1.0.8.dist-info/METADATA
vior_cli-1.0.8.dist-info/WHEEL
vior_cli-1.0.8.dist-info/entry_points.txt
vior_cli-1.0.8.dist-info/top_level.txt
vior_cli-1.0.8.dist-info/RECORD
