Metadata-Version: 2.4
Name: vior-cli
Version: 1.0.8
Summary: Vior Secrets CLI - Secure command-line interface for Vior Secrets management
Home-page: https://github.com/viorcloud/vior-cli
Author: Viorcloud Team
Author-email: Viorcloud Team <support@viorcloud.com>
Maintainer-email: Viorcloud Team <support@viorcloud.com>
License: MIT
Project-URL: Homepage, https://viorcloud.com
Project-URL: Documentation, https://docs.viorcloud.com
Project-URL: Repository, https://github.com/viorcloud/vior-cli
Project-URL: Bug Tracker, https://github.com/viorcloud/vior-cli/issues
Keywords: secrets,cli,security,encryption,vior,viorcloud
Classifier: Development Status :: 5 - Production/Stable
Classifier: Intended Audience :: Developers
Classifier: License :: OSI Approved :: MIT License
Classifier: Operating System :: OS Independent
Classifier: Programming Language :: Python :: 3
Classifier: Programming Language :: Python :: 3.7
Classifier: Programming Language :: Python :: 3.8
Classifier: Programming Language :: Python :: 3.9
Classifier: Programming Language :: Python :: 3.10
Classifier: Programming Language :: Python :: 3.11
Classifier: Topic :: Security
Classifier: Topic :: System :: Systems Administration
Classifier: Topic :: Utilities
Requires-Python: >=3.7
License-File: LICENSE
Requires-Dist: click>=8.0.0
Requires-Dist: requests>=2.25.0
Requires-Dist: cryptography>=3.4.0
Provides-Extra: dev
Requires-Dist: pytest>=6.0; extra == "dev"
Requires-Dist: black>=21.0; extra == "dev"
Requires-Dist: flake8>=3.8; extra == "dev"
Requires-Dist: mypy>=0.812; extra == "dev"
Dynamic: author
Dynamic: home-page
Dynamic: license-file
Dynamic: requires-python
